nexsys_core-0.2.0.dist-info/METADATA
nexsys_core-0.2.0.dist-info/WHEEL
nexsys_core/__init__.py
nexsys_core/nexsys_core.cp39-win_amd64.pyd
nexsys_core-0.2.0.dist-info/RECORD
