Metadata-Version: 2.1
Name: nexsys-core
Version: 0.2.0
Summary: Solve nonlinear systems of equations using Newton's method.
License: GPL-3.0-or-later
